machc/core/__init__.py
machc/core/entities/__init__.py
machc/core/entities/base/__init__.py
machc/core/entities/base/contact/__init__.py
machc/core/entities/base/contact/address.py
machc/core/entities/base/contact/address_id.py
machc/core/entities/base/identifier/__init__.py
machc/core/entities/base/identifier/entity_id.py
machc/core/entities/user/__init__.py
machc/core/entities/user/authenticated_person.py
machc/core/entities/user/login_credential.py
machc/core/entities/user/person.py
machc/core/entities/user/user.py
machc/core/entities/user/user_id.py
machc/core/entities/user/user_profile.py
machc/core/interactors/__init__.py
machc/core/interactors/user/__init__.py
machc/core/interactors/user/login.py
machc/core/interactors/user/registration.py
machc/core/interactors/user/exception/__init__.py
machc/core/interactors/user/exception/user_exception.py
machc/core/interactors/user/stud/__init__.py
machc/core/interactors/user/stud/user_login_service.py
machc/core/interactors/user/stud/user_registration_service.py
machc_core-0.0.1.dist-info/METADATA
machc_core-0.0.1.dist-info/WHEEL
machc_core-0.0.1.dist-info/top_level.txt
machc_core-0.0.1.dist-info/RECORD
