Metadata-Version: 2.4
Name: machc.core
Version: 0.0.1
Summary: Provides entities and interactors for the e-commerce business domain.
Author-email: Viktor Tovstyi <viktor.tovstyi@gmail.com>
Requires-Python: ==3.8.0
